context_mcp/__init__.py
context_mcp/server.py
context_engineering_mcp_slicenfer-0.1.0.dist-info/METADATA
context_engineering_mcp_slicenfer-0.1.0.dist-info/WHEEL
context_engineering_mcp_slicenfer-0.1.0.dist-info/entry_points.txt
context_engineering_mcp_slicenfer-0.1.0.dist-info/RECORD
