Metadata-Version: 2.4
Name: context-engineering-mcp-slicenfer
Version: 0.1.0
Summary: A Model Context Protocol (MCP) server for Context Engineering - file system as external memory for AI agents
Project-URL: Homepage, https://github.com/slicenferqin/ctx-mcp
Project-URL: Repository, https://github.com/slicenferqin/ctx-mcp
Project-URL: Issues, https://github.com/slicenferqin/ctx-mcp/issues
Author: Context Engineering Contributors
License: MIT
Keywords: agent,ai,claude,context-engineering,llm,mcp
Classifier: Development Status :: 4 - Beta
Classifier: Intended Audience :: Developers
Classifier: License :: OSI Approved :: MIT License
Classifier: Programming Language :: Python :: 3
Classifier: Programming Language :: Python :: 3.10
Classifier: Programming Language :: Python :: 3.11
Classifier: Programming Language :: Python :: 3.12
Classifier: Topic :: Software Development :: Libraries :: Python Modules
Requires-Python: >=3.10
Requires-Dist: mcp>=0.1.0
